Metadata-Version: 2.1
Name: cloudflare-dt
Version: 2.19.4
Summary: Python wrapper for the Cloudflare v4 API
Home-page: https://github.com/cloudflare/python-cloudflare
Author: Martin J. Levy
Author-email: mahtin@mahtin.com
License: MIT
Project-URL: Documentation, https://python-cloudflare.readthedocs.io/
Project-URL: API Documentaton, https://developers.cloudflare.com/api/
Project-URL: Source Code, https://github.com/cloudflare/python-cloudflare
Keywords: cloudflare
Classifier: Development Status :: 5 - Production/Stable
Classifier: Intended Audience :: Developers
Classifier: Topic :: Software Development :: Libraries :: Python Modules
Classifier: License :: OSI Approved :: MIT License
Classifier: Programming Language :: Python
Classifier: Programming Language :: Python :: 3
Classifier: Programming Language :: Python :: 3.6
Classifier: Programming Language :: Python :: 3.7
Classifier: Programming Language :: Python :: 3.8
Classifier: Programming Language :: Python :: 3.9
Classifier: Programming Language :: Python :: 3.10
Classifier: Programming Language :: Python :: 3.11
Classifier: Programming Language :: Python :: 3 :: Only
Requires-Python: >3.6.0
License-File: LICENSE
Requires-Dist: requests
Requires-Dist: pyyaml
Requires-Dist: jsonlines
Provides-Extra: test
Requires-Dist: pytest ; extra == 'test'
